Metadata-Version: 1.1
Name: django-timestampable-model
Version: 0.1.4
Summary: A simple Django model mixin for timestampable models
Home-page: https://github.com/achedeuzot/django-timestampable
Author: Klemen Sever
Author-email: klemen@achedeuzot.me
License: BSD License
Download-URL: https://github.com/achedeuzot/django-timestampable/tarball/0.1.4
Platform: UNKNOWN
Classifier: Development Status :: 5 - Production/Stable
Classifier: Environment :: Web Environment
Classifier: Framework :: Django
Classifier: Intended Audience :: Developers
Classifier: License :: OSI Approved :: BSD License
Classifier: Operating System :: OS Independent
Classifier: Programming Language :: Python
Classifier: Programming Language :: Python :: 2.7
Classifier: Programming Language :: Python :: 3
Classifier: Topic :: Internet :: WWW/HTTP
Classifier: Topic :: Internet :: WWW/HTTP :: Dynamic Content
